{
"mar_bp":{"title":"ブースターパック Marvel/Card Collection","date":"2021/12/24"}
,"bp2_all":{"title":"ブースターパック アサルトリリィ Vol.2","date":"2022/01/14"}
,"bp_gu_reedit":{"title":"ブースターパック ご注文はうさぎですか？ Re:Edit","date":"2022/01/28"}
,"pjs_bp":{"title":"ブースターパック プロジェクトセカイ カラフルステージ！ feat. 初音ミク","date":"2022/02/11"}
,"new_title_ws":{"title":"小林さんちのメイドラゴン","date":"2022/04/08"}
,"new_title_ws/#1":{"title":"Bang Dream! 5th Anniversary","date":"2022/03/16"}
,"new_title_ws/#2":{"title":"東京卍リベンジャーズ","date":"2022/05/14"}
}
